setup.py
django_stats/__init__.py
django_stats/parsers.py
django_stats/processors.py
django_stats/stats_log.py
django_stats/utils.py
django_stats_report.egg-info/PKG-INFO
django_stats_report.egg-info/SOURCES.txt
django_stats_report.egg-info/dependency_links.txt
django_stats_report.egg-info/top_level.txt