Metadata-Version: 1.0
Name: django-stats-report
Version: 0.0.1beta
Summary: Generate statistics about view usage
Home-page: UNKNOWN
Author: Vialink
Author-email: vialink@vialink.com.br
License: Proprietay Software
Platform: UNKNOWN
